sqlagent/__init__.py
sqlagent/agent.py
sqlagent/components/sql_parser_component.py
sqlagent/ingestions/load_and_persist_object_index.py
sqlagent/ingestions/load_and_persist_tables_row.py
sqlagent-1.0.8.dist-info/LICENSE
sqlagent-1.0.8.dist-info/METADATA
sqlagent-1.0.8.dist-info/WHEEL
sqlagent-1.0.8.dist-info/entry_points.txt
sqlagent-1.0.8.dist-info/RECORD
