Metadata-Version: 2.1
Name: sqlagent
Version: 1.0.8
Summary: SQL agent, query your database
Author: vikyw89
Author-email: vikyw89@gmail.com
Requires-Python: >=3.10,<3.13
Classifier: Programming Language :: Python :: 3
Classifier: Programming Language :: Python :: 3.10
Classifier: Programming Language :: Python :: 3.11
Classifier: Programming Language :: Python :: 3.12
Requires-Dist: llama-index (>=0.10.00,<0.11.0)
Requires-Dist: llama-index-embeddings-openai (>=0.1.00,<0.2.0)
Requires-Dist: llama-index-vector-stores-pinecone (>=0.1.0,<0.2.0)
Requires-Dist: llmtext (==1.0.0)
Requires-Dist: pinecone (>=4.0.0,<5.0.0)
Requires-Dist: pymysql (>=1.1.0,<2.0.0)
Requires-Dist: python-dotenv (>=1.0.0,<2.0.0)
